pynaim/__init__.py
pynaim/__main__.py
pynaim/cli.py
pynaim/controller.py
pynaim-0.1.2.dist-info/licenses/LICENSE
pynaim-0.1.2.dist-info/METADATA
pynaim-0.1.2.dist-info/WHEEL
pynaim-0.1.2.dist-info/entry_points.txt
pynaim-0.1.2.dist-info/top_level.txt
pynaim-0.1.2.dist-info/RECORD
