Metadata-Version: 2.4
Name: pynaim
Version: 0.1.2
Summary: Python client and CLI for Naim Mu-so 2nd Gen (unofficial).
Author: Joeri Blaauboer
License-Expression: MIT
Project-URL: Homepage, https://github.com/blaauboer/pynaim
Project-URL: Issues, https://github.com/blaauboer/pynaim/issues
Keywords: naim,muso,audio,home-assistant,sse,asyncio
Classifier: Programming Language :: Python :: 3
Classifier: Topic :: Multimedia :: Sound/Audio
Classifier: Topic :: Home Automation
Requires-Python: >=3.9
License-File: LICENSE
Dynamic: license-file
